ucrel_api/__init__.py
ucrel_api/_nbdev.py
ucrel_api/api.py
ucrel_api/ucrel_doc.py
ucrel_api/ucrel_token.py
ucrel_api-0.0.2.dist-info/LICENSE
ucrel_api-0.0.2.dist-info/METADATA
ucrel_api-0.0.2.dist-info/WHEEL
ucrel_api-0.0.2.dist-info/top_level.txt
ucrel_api-0.0.2.dist-info/RECORD
