Metadata-Version: 2.1
Name: ucrel-api
Version: 0.0.2
Summary: Python API to the UCREL Tool Chain
Home-page: https://github.com/UCREL/ucrel-python-api/tree/main/
Author: Andrew Moore
Author-email: andrew.p.moore94@gmail.com
License: GNU General Public License v3
Keywords: natural-language-processing nlp
Platform: UNKNOWN
Classifier: Development Status :: 4 - Beta
Classifier: Intended Audience :: Developers
Classifier: Natural Language :: English
Classifier: Programming Language :: Python :: 3.6
Classifier: Programming Language :: Python :: 3.7
Classifier: Programming Language :: Python :: 3.8
Classifier: License :: OSI Approved :: GNU General Public License v3 (GPLv3)
Requires-Python: >=3.6
Requires-Dist: requests
Provides-Extra: dev
Requires-Dist: nbdev ; extra == 'dev'
Requires-Dist: pytest ; extra == 'dev'
Requires-Dist: pytest-cov ; extra == 'dev'
Requires-Dist: twine ; extra == 'dev'
Requires-Dist: responses ; extra == 'dev'
